flow_insight/__init__.py
flow_insight/cli.py
flow_insight/client.py
flow_insight/engine.py
flow_insight/api/__init__.py
flow_insight/api/base.py
flow_insight/api/fastapi_api.py
flow_insight/dap/__init__.py
flow_insight/dap/client.py
flow_insight/storage/__init__.py
flow_insight/storage/snapshot/__init__.py
flow_insight/storage/snapshot/base.py
flow_insight/storage/snapshot/memory_backend.py
flow_insight/storage/snapshot/model.py
flow_insight/storage/snapshot/snapshot.py
flow_insight/storage_client/__init__.py
flow_insight/storage_client/base.py
flow_insight/storage_client/http_client.py
flow_insight/visualize/__init__.py
flow_insight/visualize/client.py
flow_insight/visualize/decorator.py
flow_insight/visualize/registry.py
flow_insight-1.1.1.dist-info/METADATA
flow_insight-1.1.1.dist-info/WHEEL
flow_insight-1.1.1.dist-info/entry_points.txt
flow_insight-1.1.1.dist-info/top_level.txt
flow_insight-1.1.1.dist-info/RECORD
